gpytorch_mogp/__init__.py
gpytorch_mogp/kernels/__init__.py
gpytorch_mogp/kernels/multioutput_kernel.py
gpytorch_mogp/likelihoods/__init__.py
gpytorch_mogp/likelihoods/multioutput_gaussian_likelihood.py
gpytorch_mogp/likelihoods/noise_models.py
gpytorch_mogp/utils/__init__.py
gpytorch_mogp/utils/blocks.py
gpytorch_mogp/utils/covariance.py
gpytorch_mogp-0.1.2.dist-info/METADATA
gpytorch_mogp-0.1.2.dist-info/WHEEL
gpytorch_mogp-0.1.2.dist-info/licenses/LICENSE
gpytorch_mogp-0.1.2.dist-info/RECORD
