Metadata-Version: 2.3
Name: gpytorch-mogp
Version: 0.1.2
Summary: A package which extends GPyTorch with correlated multi-output GPs
Project-URL: Documentation, https://github.com/dnv-opensource/gpytorch-mogp#readme
Project-URL: Issues, https://github.com/dnv-opensource/gpytorch-mogp/issues
Project-URL: Source, https://github.com/dnv-opensource/gpytorch-mogp
Author-email: Magnus Kristiansen <magnus.kristiansen@dnv.com>
License: MIT License
Classifier: Development Status :: 3 - Alpha
Classifier: License :: OSI Approved :: MIT License
Classifier: Programming Language :: Python :: 3.11
Classifier: Programming Language :: Python :: 3.12
Requires-Python: >=3.11
Requires-Dist: einops>=0.8.0
Requires-Dist: gpytorch~=1.11
Provides-Extra: all
Requires-Dist: jupyter>=1.0.0; extra == 'all'
Requires-Dist: matplotlib>=3.8.4; extra == 'all'
Requires-Dist: ruff>=0.4.2; extra == 'all'
Provides-Extra: dev
Requires-Dist: ruff>=0.4.2; extra == 'dev'
Provides-Extra: examples
Requires-Dist: jupyter>=1.0.0; extra == 'examples'
Requires-Dist: matplotlib>=3.8.4; extra == 'examples'
